db_engine_factory/__init__.py
db_engine_factory/cli.py
db_engine_factory/db_connection.py
db_engine_factory-0.1.5.dist-info/LICENSE
db_engine_factory-0.1.5.dist-info/METADATA
db_engine_factory-0.1.5.dist-info/WHEEL
db_engine_factory-0.1.5.dist-info/entry_points.txt
db_engine_factory-0.1.5.dist-info/top_level.txt
db_engine_factory-0.1.5.dist-info/RECORD
