Metadata-Version: 2.1
Name: db_engine_factory
Version: 0.1.5
Summary: DB Engine Factory: Simplify connecting to MySQL, MSSQL, and PostgreSQL databases through a single, unified configuration.
Author-email: Will Palmer <will@willpalmer.co.uk>
License: MIT
Project-URL: Homepage, https://github.com/skyblue-will/db_engine_factory
Project-URL: Documentation, https://github.com/skyblue-will/db_engine_factory#readme
Project-URL: Source, https://github.com/skyblue-will/db_engine_factory
Project-URL: Tracker, https://github.com/skyblue-will/db_engine_factory/issues
Keywords: database,SQLAlchemy,MySQL,PostgreSQL,MSSQL,database engine factory
Classifier: Development Status :: 3 - Alpha
Classifier: Intended Audience :: Developers
Classifier: License :: OSI Approved :: MIT License
Classifier: Programming Language :: Python :: 3
Classifier: Programming Language :: Python :: 3.6
Classifier: Programming Language :: Python :: 3.7
Classifier: Programming Language :: Python :: 3.8
Classifier: Programming Language :: Python :: 3.9
Classifier: Programming Language :: Python :: 3.10
Classifier: Operating System :: OS Independent
Classifier: Topic :: Database
Classifier: Topic :: Software Development :: Libraries
Requires-Python: >=3.6
License-File: LICENSE
Requires-Dist: python-dotenv>=1.0.0
Requires-Dist: SQLAlchemy>=2.0.25
Requires-Dist: pyodbc>=5.0.1
Requires-Dist: pymysql
Requires-Dist: psycopg2-binary
